pyscenarios/__init__.py
pyscenarios/copula.py
pyscenarios/duck.py
pyscenarios/py.typed
pyscenarios/stats.py
pyscenarios/typing.py
pyscenarios/__pycache__/sobol._calc_v-66.py312.1.nbc
pyscenarios/__pycache__/sobol._calc_v-66.py312.nbi
pyscenarios/__pycache__/sobol._calc_v-67.py312.1.nbc
pyscenarios/__pycache__/sobol._calc_v-67.py312.nbi
pyscenarios/__pycache__/sobol._calc_v-70.py312.1.nbc
pyscenarios/__pycache__/sobol._calc_v-70.py312.nbi
pyscenarios/__pycache__/sobol._calc_v-70.py38.1.nbc
pyscenarios/__pycache__/sobol._calc_v-70.py38.nbi
pyscenarios/__pycache__/sobol._calc_v-71.py312.1.nbc
pyscenarios/__pycache__/sobol._calc_v-71.py312.nbi
pyscenarios/__pycache__/sobol._sobol_kernel_jit-106.py312.1.nbc
pyscenarios/__pycache__/sobol._sobol_kernel_jit-106.py312.nbi
pyscenarios/__pycache__/sobol._sobol_kernel_jit-107.py312.1.nbc
pyscenarios/__pycache__/sobol._sobol_kernel_jit-107.py312.nbi
pyscenarios/__pycache__/sobol._sobol_kernel_jit-108.py312.1.nbc
pyscenarios/__pycache__/sobol._sobol_kernel_jit-108.py312.nbi
pyscenarios/__pycache__/sobol._sobol_kernel_jit-109.py312.1.nbc
pyscenarios/__pycache__/sobol._sobol_kernel_jit-109.py312.nbi
pyscenarios/__pycache__/sobol._sobol_kernel_jit-110.py312.1.nbc
pyscenarios/__pycache__/sobol._sobol_kernel_jit-110.py312.nbi
pyscenarios/__pycache__/sobol._sobol_kernel_jit-111.py312.1.nbc
pyscenarios/__pycache__/sobol._sobol_kernel_jit-111.py312.nbi
pyscenarios/__pycache__/sobol._sobol_kernel_jit-111.py38.1.nbc
pyscenarios/__pycache__/sobol._sobol_kernel_jit-111.py38.nbi
pyscenarios/__pycache__/sobol._sobol_kernel_jit-112.py312.1.nbc
pyscenarios/__pycache__/sobol._sobol_kernel_jit-112.py312.nbi
pyscenarios/_sobol/__init__.py
pyscenarios/_sobol/_kernel_numba.py
pyscenarios/_sobol/_kernel_numpy.py
pyscenarios/_sobol/_sobol.py
pyscenarios/_sobol/_vmatrix.py
pyscenarios/_sobol/new-joe-kuo-6.21201.txt.xz
pyscenarios/_sobol/__pycache__/_kernel_numba._sobol_kernel_jit-23.py312.1.nbc
pyscenarios-0.6.0.dist-info/licenses/LICENSE
pyscenarios-0.6.0.dist-info/METADATA
pyscenarios-0.6.0.dist-info/WHEEL
pyscenarios-0.6.0.dist-info/top_level.txt
pyscenarios-0.6.0.dist-info/RECORD
