Metadata-Version: 2.4
Name: pyscenarios
Version: 0.6.0
Summary: Python Monte Carlo Scenario Generator
Author-email: Guido Imperiale <guido.imperiale@gmail.com>
License: Apache
Project-URL: Homepage, https://github.com/crusaderky/pyscenarios
Project-URL: Bug Tracker, https://github.com/crusaderky/pyscenarios/issues
Project-URL: Changelog, https://pyscenarios.readthedocs.io/en/latest/whats-new.html
Classifier: Development Status :: 3 - Alpha
Classifier: License :: OSI Approved :: Apache Software License
Classifier: Operating System :: OS Independent
Classifier: Intended Audience :: Science/Research
Classifier: Programming Language :: Python
Classifier: Programming Language :: Python :: 3
Classifier: Programming Language :: Python :: 3 :: Only
Classifier: Programming Language :: Python :: 3.10
Classifier: Programming Language :: Python :: 3.11
Classifier: Programming Language :: Python :: 3.12
Classifier: Programming Language :: Python :: 3.13
Classifier: Topic :: Scientific/Engineering
Requires-Python: >=3.10
License-File: LICENSE
Requires-Dist: dask[array]>=2022.4.0
Requires-Dist: numpy>=1.22
Requires-Dist: scipy>=1.7
Provides-Extra: numba
Requires-Dist: numba>=0.56; extra == "numba"
Provides-Extra: all
Requires-Dist: numba>=0.56; extra == "all"
Dynamic: license-file
